{
    "title": {
        "media": {
          "url": "/ballotproposals/assets/img/banner.png",
          "caption": null,
          "credit": "Michigan Statewide Ballot Proposals"
        },
        "text": {
          "headline": "Michigan Statewide Ballot Proposals Timeline",
          "text": "Images of Michigan statewide ballot proposals scanned to PDF format from 1931-1999."
        }
    },
    "events": [
      {
        "media": {
          "url": "https://cdm16110.contentdm.oclc.org/utils/getthumbnail/collection/p16110coll7/id/104541",
          "caption": "1931 Michigan Ballot Proposals",
          "link": "/ballotproposals/items/cdm104541.html",
          "credit": "Michigan Statewide Ballot Proposals"
        },
        "start_date": { 
          "year": "1931"
        },
        "text": {
          "headline": "1931 Michigan Ballot Proposals"
        }
      },{
        "media": {
          "url": "https://cdm16110.contentdm.oclc.org/utils/getthumbnail/collection/p16110coll7/id/104548",
          "caption": "1932 Michigan Ballot Proposals",
          "link": "/ballotproposals/items/cdm104548.html",
          "credit": "Michigan Statewide Ballot Proposals"
        },
        "start_date": { 
          "year": "1932"
        },
        "text": {
          "headline": "1932 Michigan Ballot Proposals"
        }
      },{
        "media": {
          "url": "https://cdm16110.contentdm.oclc.org/utils/getthumbnail/collection/p16110coll7/id/104542",
          "caption": "1934 Michigan Ballot Proposals",
          "link": "/ballotproposals/items/cdm104542.html",
          "credit": "Michigan Statewide Ballot Proposals"
        },
        "start_date": { 
          "year": "1934"
        },
        "text": {
          "headline": "1934 Michigan Ballot Proposals"
        }
      },{
        "media": {
          "url": "https://cdm16110.contentdm.oclc.org/utils/getthumbnail/collection/p16110coll7/id/104543",
          "caption": "1935 Michigan Ballot Propsal",
          "link": "/ballotproposals/items/cdm104543.html",
          "credit": "Michigan Statewide Ballot Proposals"
        },
        "start_date": { 
          "year": "1935"
        },
        "text": {
          "headline": "1935 Michigan Ballot Propsal"
        }
      },{
        "media": {
          "url": "https://cdm16110.contentdm.oclc.org/utils/getthumbnail/collection/p16110coll7/id/104544",
          "caption": "1936 Michigan Ballot Proposals",
          "link": "/ballotproposals/items/cdm104544.html",
          "credit": "Michigan Statewide Ballot Proposals"
        },
        "start_date": { 
          "year": "1936"
        },
        "text": {
          "headline": "1936 Michigan Ballot Proposals"
        }
      },{
        "media": {
          "url": "https://cdm16110.contentdm.oclc.org/utils/getthumbnail/collection/p16110coll7/id/104545",
          "caption": "1938 Michigan Ballot Proposals",
          "link": "/ballotproposals/items/cdm104545.html",
          "credit": "Michigan Statewide Ballot Proposals"
        },
        "start_date": { 
          "year": "1938"
        },
        "text": {
          "headline": "1938 Michigan Ballot Proposals"
        }
      },{
        "media": {
          "url": "https://cdm16110.contentdm.oclc.org/utils/getthumbnail/collection/p16110coll7/id/104546",
          "caption": "1939 Michigan Ballot Proposals",
          "link": "/ballotproposals/items/cdm104546.html",
          "credit": "Michigan Statewide Ballot Proposals"
        },
        "start_date": { 
          "year": "1939"
        },
        "text": {
          "headline": "1939 Michigan Ballot Proposals"
        }
      },{
        "media": {
          "url": "https://cdm16110.contentdm.oclc.org/utils/getthumbnail/collection/p16110coll7/id/104547",
          "caption": "1940 Michigan Ballot Proposals",
          "link": "/ballotproposals/items/cdm104547.html",
          "credit": "Michigan Statewide Ballot Proposals"
        },
        "start_date": { 
          "year": "1940"
        },
        "text": {
          "headline": "1940 Michigan Ballot Proposals"
        }
      },{
        "media": {
          "url": "https://cdm16110.contentdm.oclc.org/utils/getthumbnail/collection/p16110coll7/id/104558",
          "caption": "1942 Michigan Ballot Proposals",
          "link": "/ballotproposals/items/cdm104558.html",
          "credit": "Michigan Statewide Ballot Proposals"
        },
        "start_date": { 
          "year": "1942"
        },
        "text": {
          "headline": "1942 Michigan Ballot Proposals"
        }
      },{
        "media": {
          "url": "https://cdm16110.contentdm.oclc.org/utils/getthumbnail/collection/p16110coll7/id/104559",
          "caption": "1944 Michigan Ballot Proposals",
          "link": "/ballotproposals/items/cdm104559.html",
          "credit": "Michigan Statewide Ballot Proposals"
        },
        "start_date": { 
          "year": "1944"
        },
        "text": {
          "headline": "1944 Michigan Ballot Proposals"
        }
      },{
        "media": {
          "url": "https://cdm16110.contentdm.oclc.org/utils/getthumbnail/collection/p16110coll7/id/104530",
          "caption": "1968 (August) Michigan Ballot Proposals",
          "link": "/ballotproposals/items/cdm104530.html",
          "credit": "Michigan Statewide Ballot Proposals"
        },
        "start_date": { 
          "month": "08",
          "day": "",
          "year": "1968"
        },
        "text": {
          "headline": "1968 (August) Michigan Ballot Proposals"
        }
      },{
        "media": {
          "url": "https://cdm16110.contentdm.oclc.org/utils/getthumbnail/collection/p16110coll7/id/104531",
          "caption": "1968 (November) Michigan Ballot Proposals",
          "link": "/ballotproposals/items/cdm104531.html",
          "credit": "Michigan Statewide Ballot Proposals"
        },
        "start_date": { 
          "month": "11",
          "day": "",
          "year": "1968"
        },
        "text": {
          "headline": "1968 (November) Michigan Ballot Proposals"
        }
      },{
        "media": {
          "url": "https://cdm16110.contentdm.oclc.org/utils/getthumbnail/collection/p16110coll7/id/104490",
          "caption": "1972 (August) Michigan Ballot Proposal 'A'",
          "link": "/ballotproposals/items/cdm104490.html",
          "credit": "Michigan Statewide Ballot Proposals"
        },
        "start_date": { 
          "month": "08",
          "day": "",
          "year": "1972"
        },
        "text": {
          "headline": "1972 (August) Michigan Ballot Proposal 'A'"
        }
      },{
        "media": {
          "url": "https://cdm16110.contentdm.oclc.org/utils/getthumbnail/collection/p16110coll7/id/104491",
          "caption": "1972 (May) Michigan Ballot Proposal 'A'",
          "link": "/ballotproposals/items/cdm104491.html",
          "credit": "Michigan Statewide Ballot Proposals"
        },
        "start_date": { 
          "month": "05",
          "day": "",
          "year": "1972"
        },
        "text": {
          "headline": "1972 (May) Michigan Ballot Proposal 'A'"
        }
      },{
        "media": {
          "url": "https://cdm16110.contentdm.oclc.org/utils/getthumbnail/collection/p16110coll7/id/104492",
          "caption": "1972 (May) Michigan Ballot Proposal 'B'",
          "link": "/ballotproposals/items/cdm104492.html",
          "credit": "Michigan Statewide Ballot Proposals"
        },
        "start_date": { 
          "month": "05",
          "day": "",
          "year": "1972"
        },
        "text": {
          "headline": "1972 (May) Michigan Ballot Proposal 'B'"
        }
      },{
        "media": {
          "url": "https://cdm16110.contentdm.oclc.org/utils/getthumbnail/collection/p16110coll7/id/104493",
          "caption": "1972 (November) Michigan Ballot Proposal 'A'",
          "link": "/ballotproposals/items/cdm104493.html",
          "credit": "Michigan Statewide Ballot Proposals"
        },
        "start_date": { 
          "month": "11",
          "day": "",
          "year": "1972"
        },
        "text": {
          "headline": "1972 (November) Michigan Ballot Proposal 'A'"
        }
      },{
        "media": {
          "url": "https://cdm16110.contentdm.oclc.org/utils/getthumbnail/collection/p16110coll7/id/104494",
          "caption": "1972 (November) Michigan Ballot Proposal 'B'",
          "link": "/ballotproposals/items/cdm104494.html",
          "credit": "Michigan Statewide Ballot Proposals"
        },
        "start_date": { 
          "month": "11",
          "day": "",
          "year": "1972"
        },
        "text": {
          "headline": "1972 (November) Michigan Ballot Proposal 'B'"
        }
      },{
        "media": {
          "url": "https://cdm16110.contentdm.oclc.org/utils/getthumbnail/collection/p16110coll7/id/104495",
          "caption": "1972 (November) Michigan Ballot Proposal 'C'",
          "link": "/ballotproposals/items/cdm104495.html",
          "credit": "Michigan Statewide Ballot Proposals"
        },
        "start_date": { 
          "month": "11",
          "day": "",
          "year": "1972"
        },
        "text": {
          "headline": "1972 (November) Michigan Ballot Proposal 'C'"
        }
      },{
        "media": {
          "url": "https://cdm16110.contentdm.oclc.org/utils/getthumbnail/collection/p16110coll7/id/104496",
          "caption": "1972 (November) Michigan Ballot Proposal 'D'",
          "link": "/ballotproposals/items/cdm104496.html",
          "credit": "Michigan Statewide Ballot Proposals"
        },
        "start_date": { 
          "month": "11",
          "day": "",
          "year": "1972"
        },
        "text": {
          "headline": "1972 (November) Michigan Ballot Proposal 'D'"
        }
      },{
        "media": {
          "url": "https://cdm16110.contentdm.oclc.org/utils/getthumbnail/collection/p16110coll7/id/104497",
          "caption": "1972 (November) Michigan Ballot Proposal 'E'",
          "link": "/ballotproposals/items/cdm104497.html",
          "credit": "Michigan Statewide Ballot Proposals"
        },
        "start_date": { 
          "month": "11",
          "day": "",
          "year": "1972"
        },
        "text": {
          "headline": "1972 (November) Michigan Ballot Proposal 'E'"
        }
      },{
        "media": {
          "url": "https://cdm16110.contentdm.oclc.org/utils/getthumbnail/collection/p16110coll7/id/104508",
          "caption": "1974 Michigan Ballot Proposal 'A'",
          "link": "/ballotproposals/items/cdm104508.html",
          "credit": "Michigan Statewide Ballot Proposals"
        },
        "start_date": { 
          "year": "1974"
        },
        "text": {
          "headline": "1974 Michigan Ballot Proposal 'A'"
        }
      },{
        "media": {
          "url": "https://cdm16110.contentdm.oclc.org/utils/getthumbnail/collection/p16110coll7/id/104509",
          "caption": "1974 Michigan Ballot Proposal 'B'",
          "link": "/ballotproposals/items/cdm104509.html",
          "credit": "Michigan Statewide Ballot Proposals"
        },
        "start_date": { 
          "year": "1974"
        },
        "text": {
          "headline": "1974 Michigan Ballot Proposal 'B'"
        }
      },{
        "media": {
          "url": "https://cdm16110.contentdm.oclc.org/utils/getthumbnail/collection/p16110coll7/id/104510",
          "caption": "1974 Michigan Ballot Proposal 'C'",
          "link": "/ballotproposals/items/cdm104510.html",
          "credit": "Michigan Statewide Ballot Proposals"
        },
        "start_date": { 
          "year": "1974"
        },
        "text": {
          "headline": "1974 Michigan Ballot Proposal 'C'"
        }
      },{
        "media": {
          "url": "https://cdm16110.contentdm.oclc.org/utils/getthumbnail/collection/p16110coll7/id/104511",
          "caption": "1974 Michigan Ballot Proposal 'D'",
          "link": "/ballotproposals/items/cdm104511.html",
          "credit": "Michigan Statewide Ballot Proposals"
        },
        "start_date": { 
          "year": "1974"
        },
        "text": {
          "headline": "1974 Michigan Ballot Proposal 'D'"
        }
      },{
        "media": {
          "url": "https://cdm16110.contentdm.oclc.org/utils/getthumbnail/collection/p16110coll7/id/104528",
          "caption": "1976 Michigan Ballot Proposal 'A'",
          "link": "/ballotproposals/items/cdm104528.html",
          "credit": "Michigan Statewide Ballot Proposals"
        },
        "start_date": { 
          "year": "1976"
        },
        "text": {
          "headline": "1976 Michigan Ballot Proposal 'A'"
        }
      },{
        "media": {
          "url": "https://cdm16110.contentdm.oclc.org/utils/getthumbnail/collection/p16110coll7/id/104525",
          "caption": "1976 Michigan Ballot Proposal 'B'",
          "link": "/ballotproposals/items/cdm104525.html",
          "credit": "Michigan Statewide Ballot Proposals"
        },
        "start_date": { 
          "year": "1976"
        },
        "text": {
          "headline": "1976 Michigan Ballot Proposal 'B'"
        }
      },{
        "media": {
          "url": "https://cdm16110.contentdm.oclc.org/utils/getthumbnail/collection/p16110coll7/id/104526",
          "caption": "1976 Michigan Ballot Proposal 'C'",
          "link": "/ballotproposals/items/cdm104526.html",
          "credit": "Michigan Statewide Ballot Proposals"
        },
        "start_date": { 
          "year": "1976"
        },
        "text": {
          "headline": "1976 Michigan Ballot Proposal 'C'"
        }
      },{
        "media": {
          "url": "https://cdm16110.contentdm.oclc.org/utils/getthumbnail/collection/p16110coll7/id/104527",
          "caption": "1976 Michigan Ballot Proposal 'D'",
          "link": "/ballotproposals/items/cdm104527.html",
          "credit": "Michigan Statewide Ballot Proposals"
        },
        "start_date": { 
          "year": "1976"
        },
        "text": {
          "headline": "1976 Michigan Ballot Proposal 'D'"
        }
      },{
        "media": {
          "url": "https://cdm16110.contentdm.oclc.org/utils/getthumbnail/collection/p16110coll7/id/104513",
          "caption": "1978 Michigan Ballot Proposal 'A'",
          "link": "/ballotproposals/items/cdm104513.html",
          "credit": "Michigan Statewide Ballot Proposals"
        },
        "start_date": { 
          "year": "1978"
        },
        "text": {
          "headline": "1978 Michigan Ballot Proposal 'A'"
        }
      },{
        "media": {
          "url": "https://cdm16110.contentdm.oclc.org/utils/getthumbnail/collection/p16110coll7/id/104514",
          "caption": "1978 Michigan Ballot Proposal 'B'",
          "link": "/ballotproposals/items/cdm104514.html",
          "credit": "Michigan Statewide Ballot Proposals"
        },
        "start_date": { 
          "year": "1978"
        },
        "text": {
          "headline": "1978 Michigan Ballot Proposal 'B'"
        }
      },{
        "media": {
          "url": "https://cdm16110.contentdm.oclc.org/utils/getthumbnail/collection/p16110coll7/id/104515",
          "caption": "1978 Michigan Ballot Proposal 'C'",
          "link": "/ballotproposals/items/cdm104515.html",
          "credit": "Michigan Statewide Ballot Proposals"
        },
        "start_date": { 
          "year": "1978"
        },
        "text": {
          "headline": "1978 Michigan Ballot Proposal 'C'"
        }
      },{
        "media": {
          "url": "https://cdm16110.contentdm.oclc.org/utils/getthumbnail/collection/p16110coll7/id/104516",
          "caption": "1978 Michigan Ballot Proposal 'D'",
          "link": "/ballotproposals/items/cdm104516.html",
          "credit": "Michigan Statewide Ballot Proposals"
        },
        "start_date": { 
          "year": "1978"
        },
        "text": {
          "headline": "1978 Michigan Ballot Proposal 'D'"
        }
      },{
        "media": {
          "url": "https://cdm16110.contentdm.oclc.org/utils/getthumbnail/collection/p16110coll7/id/104517",
          "caption": "1978 Michigan Ballot Proposal 'E'",
          "link": "/ballotproposals/items/cdm104517.html",
          "credit": "Michigan Statewide Ballot Proposals"
        },
        "start_date": { 
          "year": "1978"
        },
        "text": {
          "headline": "1978 Michigan Ballot Proposal 'E'"
        }
      },{
        "media": {
          "url": "https://cdm16110.contentdm.oclc.org/utils/getthumbnail/collection/p16110coll7/id/104518",
          "caption": "1978 Michigan Ballot Proposal 'G'",
          "link": "/ballotproposals/items/cdm104518.html",
          "credit": "Michigan Statewide Ballot Proposals"
        },
        "start_date": { 
          "year": "1978"
        },
        "text": {
          "headline": "1978 Michigan Ballot Proposal 'G'"
        }
      },{
        "media": {
          "url": "https://cdm16110.contentdm.oclc.org/utils/getthumbnail/collection/p16110coll7/id/104519",
          "caption": "1978 Michigan Ballot Proposal 'H'",
          "link": "/ballotproposals/items/cdm104519.html",
          "credit": "Michigan Statewide Ballot Proposals"
        },
        "start_date": { 
          "year": "1978"
        },
        "text": {
          "headline": "1978 Michigan Ballot Proposal 'H'"
        }
      },{
        "media": {
          "url": "https://cdm16110.contentdm.oclc.org/utils/getthumbnail/collection/p16110coll7/id/104520",
          "caption": "1978 Michigan Ballot Proposal 'J'",
          "link": "/ballotproposals/items/cdm104520.html",
          "credit": "Michigan Statewide Ballot Proposals"
        },
        "start_date": { 
          "year": "1978"
        },
        "text": {
          "headline": "1978 Michigan Ballot Proposal 'J'"
        }
      },{
        "media": {
          "url": "https://cdm16110.contentdm.oclc.org/utils/getthumbnail/collection/p16110coll7/id/104521",
          "caption": "1978 Michigan Ballot Proposal 'K'",
          "link": "/ballotproposals/items/cdm104521.html",
          "credit": "Michigan Statewide Ballot Proposals"
        },
        "start_date": { 
          "year": "1978"
        },
        "text": {
          "headline": "1978 Michigan Ballot Proposal 'K'"
        }
      },{
        "media": {
          "url": "https://cdm16110.contentdm.oclc.org/utils/getthumbnail/collection/p16110coll7/id/104522",
          "caption": "1978 Michigan Ballot Proposal 'M'",
          "link": "/ballotproposals/items/cdm104522.html",
          "credit": "Michigan Statewide Ballot Proposals"
        },
        "start_date": { 
          "year": "1978"
        },
        "text": {
          "headline": "1978 Michigan Ballot Proposal 'M'"
        }
      },{
        "media": {
          "url": "https://cdm16110.contentdm.oclc.org/utils/getthumbnail/collection/p16110coll7/id/104523",
          "caption": "1978 Michigan Ballot Proposal 'R'",
          "link": "/ballotproposals/items/cdm104523.html",
          "credit": "Michigan Statewide Ballot Proposals"
        },
        "start_date": { 
          "year": "1978"
        },
        "text": {
          "headline": "1978 Michigan Ballot Proposal 'R'"
        }
      },{
        "media": {
          "url": "https://cdm16110.contentdm.oclc.org/utils/getthumbnail/collection/p16110coll7/id/104499",
          "caption": "1980 Michigan Ballot Proposals",
          "link": "/ballotproposals/items/cdm104499.html",
          "credit": "Michigan Statewide Ballot Proposals"
        },
        "start_date": { 
          "year": "1980"
        },
        "text": {
          "headline": "1980 Michigan Ballot Proposals"
        }
      },{
        "media": {
          "url": "https://cdm16110.contentdm.oclc.org/utils/getthumbnail/collection/p16110coll7/id/104500",
          "caption": "1980 Michigan Ballot Proposal 'A'",
          "link": "/ballotproposals/items/cdm104500.html",
          "credit": "Michigan Statewide Ballot Proposals"
        },
        "start_date": { 
          "year": "1980"
        },
        "text": {
          "headline": "1980 Michigan Ballot Proposal 'A'"
        }
      },{
        "media": {
          "url": "https://cdm16110.contentdm.oclc.org/utils/getthumbnail/collection/p16110coll7/id/104501",
          "caption": "1980 Michigan Ballot Proposal 'B'",
          "link": "/ballotproposals/items/cdm104501.html",
          "credit": "Michigan Statewide Ballot Proposals"
        },
        "start_date": { 
          "year": "1980"
        },
        "text": {
          "headline": "1980 Michigan Ballot Proposal 'B'"
        }
      },{
        "media": {
          "url": "https://cdm16110.contentdm.oclc.org/utils/getthumbnail/collection/p16110coll7/id/104502",
          "caption": "1980 Michigan Ballot Proposal 'C'",
          "link": "/ballotproposals/items/cdm104502.html",
          "credit": "Michigan Statewide Ballot Proposals"
        },
        "start_date": { 
          "year": "1980"
        },
        "text": {
          "headline": "1980 Michigan Ballot Proposal 'C'"
        }
      },{
        "media": {
          "url": "https://cdm16110.contentdm.oclc.org/utils/getthumbnail/collection/p16110coll7/id/104503",
          "caption": "1980 Michigan Ballot Proposal 'D'",
          "link": "/ballotproposals/items/cdm104503.html",
          "credit": "Michigan Statewide Ballot Proposals"
        },
        "start_date": { 
          "year": "1980"
        },
        "text": {
          "headline": "1980 Michigan Ballot Proposal 'D'"
        }
      },{
        "media": {
          "url": "https://cdm16110.contentdm.oclc.org/utils/getthumbnail/collection/p16110coll7/id/104504",
          "caption": "1980 Michigan Ballot Proposal 'E'",
          "link": "/ballotproposals/items/cdm104504.html",
          "credit": "Michigan Statewide Ballot Proposals"
        },
        "start_date": { 
          "year": "1980"
        },
        "text": {
          "headline": "1980 Michigan Ballot Proposal 'E'"
        }
      },{
        "media": {
          "url": "https://cdm16110.contentdm.oclc.org/utils/getthumbnail/collection/p16110coll7/id/104505",
          "caption": "1980 Michigan Ballot Proposal 'G'",
          "link": "/ballotproposals/items/cdm104505.html",
          "credit": "Michigan Statewide Ballot Proposals"
        },
        "start_date": { 
          "year": "1980"
        },
        "text": {
          "headline": "1980 Michigan Ballot Proposal 'G'"
        }
      },{
        "media": {
          "url": "https://cdm16110.contentdm.oclc.org/utils/getthumbnail/collection/p16110coll7/id/104506",
          "caption": "1980 Michigan Ballot Proposal 'H'",
          "link": "/ballotproposals/items/cdm104506.html",
          "credit": "Michigan Statewide Ballot Proposals"
        },
        "start_date": { 
          "year": "1980"
        },
        "text": {
          "headline": "1980 Michigan Ballot Proposal 'H'"
        }
      },{
        "media": {
          "url": "https://cdm16110.contentdm.oclc.org/utils/getthumbnail/collection/p16110coll7/id/104553",
          "caption": "1981 Michigan Ballot Proposal 'A'",
          "link": "/ballotproposals/items/cdm104553.html",
          "credit": "Michigan Statewide Ballot Proposals"
        },
        "start_date": { 
          "year": "1981"
        },
        "text": {
          "headline": "1981 Michigan Ballot Proposal 'A'"
        }
      },{
        "media": {
          "url": "https://cdm16110.contentdm.oclc.org/utils/getthumbnail/collection/p16110coll7/id/104464",
          "caption": "1982 Michigan Ballot Proposals",
          "link": "/ballotproposals/items/cdm104464.html",
          "credit": "Michigan Statewide Ballot Proposals"
        },
        "start_date": { 
          "year": "1982"
        },
        "text": {
          "headline": "1982 Michigan Ballot Proposals"
        }
      },{
        "media": {
          "url": "https://cdm16110.contentdm.oclc.org/utils/getthumbnail/collection/p16110coll7/id/104465",
          "caption": "1982 Michigan Ballot Proposal 'A'",
          "link": "/ballotproposals/items/cdm104465.html",
          "credit": "Michigan Statewide Ballot Proposals"
        },
        "start_date": { 
          "year": "1982"
        },
        "text": {
          "headline": "1982 Michigan Ballot Proposal 'A'"
        }
      },{
        "media": {
          "url": "https://cdm16110.contentdm.oclc.org/utils/getthumbnail/collection/p16110coll7/id/104466",
          "caption": "1982 Michigan Ballot Proposal 'B'",
          "link": "/ballotproposals/items/cdm104466.html",
          "credit": "Michigan Statewide Ballot Proposals"
        },
        "start_date": { 
          "year": "1982"
        },
        "text": {
          "headline": "1982 Michigan Ballot Proposal 'B'"
        }
      },{
        "media": {
          "url": "https://cdm16110.contentdm.oclc.org/utils/getthumbnail/collection/p16110coll7/id/104467",
          "caption": "1982 Michigan Ballot Proposal 'C'",
          "link": "/ballotproposals/items/cdm104467.html",
          "credit": "Michigan Statewide Ballot Proposals"
        },
        "start_date": { 
          "year": "1982"
        },
        "text": {
          "headline": "1982 Michigan Ballot Proposal 'C'"
        }
      },{
        "media": {
          "url": "https://cdm16110.contentdm.oclc.org/utils/getthumbnail/collection/p16110coll7/id/104468",
          "caption": "1982 Michigan Ballot Proposal 'D'",
          "link": "/ballotproposals/items/cdm104468.html",
          "credit": "Michigan Statewide Ballot Proposals"
        },
        "start_date": { 
          "year": "1982"
        },
        "text": {
          "headline": "1982 Michigan Ballot Proposal 'D'"
        }
      },{
        "media": {
          "url": "https://cdm16110.contentdm.oclc.org/utils/getthumbnail/collection/p16110coll7/id/104469",
          "caption": "1982 Michigan Ballot Proposal 'E'",
          "link": "/ballotproposals/items/cdm104469.html",
          "credit": "Michigan Statewide Ballot Proposals"
        },
        "start_date": { 
          "year": "1982"
        },
        "text": {
          "headline": "1982 Michigan Ballot Proposal 'E'"
        }
      },{
        "media": {
          "url": "https://cdm16110.contentdm.oclc.org/utils/getthumbnail/collection/p16110coll7/id/104470",
          "caption": "1982 Michigan Ballot Proposal 'G'",
          "link": "/ballotproposals/items/cdm104470.html",
          "credit": "Michigan Statewide Ballot Proposals"
        },
        "start_date": { 
          "year": "1982"
        },
        "text": {
          "headline": "1982 Michigan Ballot Proposal 'G'"
        }
      },{
        "media": {
          "url": "https://cdm16110.contentdm.oclc.org/utils/getthumbnail/collection/p16110coll7/id/104471",
          "caption": "1982 Michigan Ballot Proposal 'H'",
          "link": "/ballotproposals/items/cdm104471.html",
          "credit": "Michigan Statewide Ballot Proposals"
        },
        "start_date": { 
          "year": "1982"
        },
        "text": {
          "headline": "1982 Michigan Ballot Proposal 'H'"
        }
      },{
        "media": {
          "url": "https://cdm16110.contentdm.oclc.org/utils/getthumbnail/collection/p16110coll7/id/104457",
          "caption": "1984 Michigan Ballot Proposals",
          "link": "/ballotproposals/items/cdm104457.html",
          "credit": "Michigan Statewide Ballot Proposals"
        },
        "start_date": { 
          "year": "1984"
        },
        "text": {
          "headline": "1984 Michigan Ballot Proposals"
        }
      },{
        "media": {
          "url": "https://cdm16110.contentdm.oclc.org/utils/getthumbnail/collection/p16110coll7/id/104458",
          "caption": "1984 Michigan Ballot Proposals (corrected)",
          "link": "/ballotproposals/items/cdm104458.html",
          "credit": "Michigan Statewide Ballot Proposals"
        },
        "start_date": { 
          "year": "1984"
        },
        "text": {
          "headline": "1984 Michigan Ballot Proposals (corrected)"
        }
      },{
        "media": {
          "url": "https://cdm16110.contentdm.oclc.org/utils/getthumbnail/collection/p16110coll7/id/104459",
          "caption": "1984 Michigan Ballot Proposal 'A'",
          "link": "/ballotproposals/items/cdm104459.html",
          "credit": "Michigan Statewide Ballot Proposals"
        },
        "start_date": { 
          "year": "1984"
        },
        "text": {
          "headline": "1984 Michigan Ballot Proposal 'A'"
        }
      },{
        "media": {
          "url": "https://cdm16110.contentdm.oclc.org/utils/getthumbnail/collection/p16110coll7/id/104460",
          "caption": "1984 Michigan Ballot Proposal 'B'",
          "link": "/ballotproposals/items/cdm104460.html",
          "credit": "Michigan Statewide Ballot Proposals"
        },
        "start_date": { 
          "year": "1984"
        },
        "text": {
          "headline": "1984 Michigan Ballot Proposal 'B'"
        }
      },{
        "media": {
          "url": "https://cdm16110.contentdm.oclc.org/utils/getthumbnail/collection/p16110coll7/id/104461",
          "caption": "1984 Michigan Ballot Proposal 'C'",
          "link": "/ballotproposals/items/cdm104461.html",
          "credit": "Michigan Statewide Ballot Proposals"
        },
        "start_date": { 
          "year": "1984"
        },
        "text": {
          "headline": "1984 Michigan Ballot Proposal 'C'"
        }
      },{
        "media": {
          "url": "https://cdm16110.contentdm.oclc.org/utils/getthumbnail/collection/p16110coll7/id/104473",
          "caption": "1986 Michigan Ballot Proposal 'A'",
          "link": "/ballotproposals/items/cdm104473.html",
          "credit": "Michigan Statewide Ballot Proposals"
        },
        "start_date": { 
          "year": "1986"
        },
        "text": {
          "headline": "1986 Michigan Ballot Proposal 'A'"
        }
      },{
        "media": {
          "url": "https://cdm16110.contentdm.oclc.org/utils/getthumbnail/collection/p16110coll7/id/104474",
          "caption": "1986 Michigan Ballot Proposal 'B'",
          "link": "/ballotproposals/items/cdm104474.html",
          "credit": "Michigan Statewide Ballot Proposals"
        },
        "start_date": { 
          "year": "1986"
        },
        "text": {
          "headline": "1986 Michigan Ballot Proposal 'B'"
        }
      },{
        "media": {
          "url": "https://cdm16110.contentdm.oclc.org/utils/getthumbnail/collection/p16110coll7/id/104475",
          "caption": "1986 Michigan Ballot Proposal 'C'",
          "link": "/ballotproposals/items/cdm104475.html",
          "credit": "Michigan Statewide Ballot Proposals"
        },
        "start_date": { 
          "year": "1986"
        },
        "text": {
          "headline": "1986 Michigan Ballot Proposal 'C'"
        }
      },{
        "media": {
          "url": "https://cdm16110.contentdm.oclc.org/utils/getthumbnail/collection/p16110coll7/id/104480",
          "caption": "1988 Michigan Ballot Proposal 'A'",
          "link": "/ballotproposals/items/cdm104480.html",
          "credit": "Michigan Statewide Ballot Proposals"
        },
        "start_date": { 
          "year": "1988"
        },
        "text": {
          "headline": "1988 Michigan Ballot Proposal 'A'"
        }
      },{
        "media": {
          "url": "https://cdm16110.contentdm.oclc.org/utils/getthumbnail/collection/p16110coll7/id/104481",
          "caption": "1988 Michigan Ballot Proposal 'B'",
          "link": "/ballotproposals/items/cdm104481.html",
          "credit": "Michigan Statewide Ballot Proposals"
        },
        "start_date": { 
          "year": "1988"
        },
        "text": {
          "headline": "1988 Michigan Ballot Proposal 'B'"
        }
      },{
        "media": {
          "url": "https://cdm16110.contentdm.oclc.org/utils/getthumbnail/collection/p16110coll7/id/104482",
          "caption": "1988 Michigan Ballot Proposal 'C'",
          "link": "/ballotproposals/items/cdm104482.html",
          "credit": "Michigan Statewide Ballot Proposals"
        },
        "start_date": { 
          "year": "1988"
        },
        "text": {
          "headline": "1988 Michigan Ballot Proposal 'C'"
        }
      },{
        "media": {
          "url": "https://cdm16110.contentdm.oclc.org/utils/getthumbnail/collection/p16110coll7/id/104483",
          "caption": "1988 Michigan Ballot Proposal 'D'",
          "link": "/ballotproposals/items/cdm104483.html",
          "credit": "Michigan Statewide Ballot Proposals"
        },
        "start_date": { 
          "year": "1988"
        },
        "text": {
          "headline": "1988 Michigan Ballot Proposal 'D'"
        }
      },{
        "media": {
          "url": "https://cdm16110.contentdm.oclc.org/utils/getthumbnail/collection/p16110coll7/id/104477",
          "caption": "1989 Michigan Ballot Proposal 'A'",
          "link": "/ballotproposals/items/cdm104477.html",
          "credit": "Michigan Statewide Ballot Proposals"
        },
        "start_date": { 
          "year": "1989"
        },
        "text": {
          "headline": "1989 Michigan Ballot Proposal 'A'"
        }
      },{
        "media": {
          "url": "https://cdm16110.contentdm.oclc.org/utils/getthumbnail/collection/p16110coll7/id/104478",
          "caption": "1989 Michigan Ballot Proposal 'B'",
          "link": "/ballotproposals/items/cdm104478.html",
          "credit": "Michigan Statewide Ballot Proposals"
        },
        "start_date": { 
          "year": "1989"
        },
        "text": {
          "headline": "1989 Michigan Ballot Proposal 'B'"
        }
      },{
        "media": {
          "url": "https://cdm16110.contentdm.oclc.org/utils/getthumbnail/collection/p16110coll7/id/104489",
          "caption": "1992 Michigan Ballot Proposal 'A'",
          "link": "/ballotproposals/items/cdm104489.html",
          "credit": "Michigan Statewide Ballot Proposals"
        },
        "start_date": { 
          "year": "1992"
        },
        "text": {
          "headline": "1992 Michigan Ballot Proposal 'A'"
        }
      },{
        "media": {
          "url": "https://cdm16110.contentdm.oclc.org/utils/getthumbnail/collection/p16110coll7/id/104486",
          "caption": "1992 Michigan Ballot Proposal 'B'",
          "link": "/ballotproposals/items/cdm104486.html",
          "credit": "Michigan Statewide Ballot Proposals"
        },
        "start_date": { 
          "year": "1992"
        },
        "text": {
          "headline": "1992 Michigan Ballot Proposal 'B'"
        }
      },{
        "media": {
          "url": "https://cdm16110.contentdm.oclc.org/utils/getthumbnail/collection/p16110coll7/id/104487",
          "caption": "1992 Michigan Ballot Proposal 'C'",
          "link": "/ballotproposals/items/cdm104487.html",
          "credit": "Michigan Statewide Ballot Proposals"
        },
        "start_date": { 
          "year": "1992"
        },
        "text": {
          "headline": "1992 Michigan Ballot Proposal 'C'"
        }
      },{
        "media": {
          "url": "https://cdm16110.contentdm.oclc.org/utils/getthumbnail/collection/p16110coll7/id/104488",
          "caption": "1992 Michigan Ballot Proposal 'D'",
          "link": "/ballotproposals/items/cdm104488.html",
          "credit": "Michigan Statewide Ballot Proposals"
        },
        "start_date": { 
          "year": "1992"
        },
        "text": {
          "headline": "1992 Michigan Ballot Proposal 'D'"
        }
      },{
        "media": {
          "url": "https://cdm16110.contentdm.oclc.org/utils/getthumbnail/collection/p16110coll7/id/104557",
          "caption": "1993 Michigan Ballot Proposal 'A'",
          "link": "/ballotproposals/items/cdm104557.html",
          "credit": "Michigan Statewide Ballot Proposals"
        },
        "start_date": { 
          "year": "1992"
        },
        "text": {
          "headline": "1993 Michigan Ballot Proposal 'A'"
        }
      },{
        "media": {
          "url": "https://cdm16110.contentdm.oclc.org/utils/getthumbnail/collection/p16110coll7/id/138411",
          "caption": "1994 (March) Michigan Ballot Proposal 'A'",
          "link": "/ballotproposals/items/cdm138411.html",
          "credit": "Michigan Statewide Ballot Proposals"
        },
        "start_date": { 
          "month": "03",
          "day": "",
          "year": "1994"
        },
        "text": {
          "headline": "1994 (March) Michigan Ballot Proposal 'A'"
        }
      },{
        "media": {
          "url": "https://cdm16110.contentdm.oclc.org/utils/getthumbnail/collection/p16110coll7/id/138412",
          "caption": "1994 (November) Michigan Ballot Proposal 'A'",
          "link": "/ballotproposals/items/cdm138412.html",
          "credit": "Michigan Statewide Ballot Proposals"
        },
        "start_date": { 
          "month": "11",
          "day": "",
          "year": "1994"
        },
        "text": {
          "headline": "1994 (November) Michigan Ballot Proposal 'A'"
        }
      },{
        "media": {
          "url": "https://cdm16110.contentdm.oclc.org/utils/getthumbnail/collection/p16110coll7/id/138413",
          "caption": "1994 (November) Michigan Ballot Proposal 'B'",
          "link": "/ballotproposals/items/cdm138413.html",
          "credit": "Michigan Statewide Ballot Proposals"
        },
        "start_date": { 
          "month": "11",
          "day": "",
          "year": "1994"
        },
        "text": {
          "headline": "1994 (November) Michigan Ballot Proposal 'B'"
        }
      },{
        "media": {
          "url": "https://cdm16110.contentdm.oclc.org/utils/getthumbnail/collection/p16110coll7/id/138414",
          "caption": "1994 (November) Michigan Ballot Proposal 'C'",
          "link": "/ballotproposals/items/cdm138414.html",
          "credit": "Michigan Statewide Ballot Proposals"
        },
        "start_date": { 
          "month": "11",
          "day": "",
          "year": "1994"
        },
        "text": {
          "headline": "1994 (November) Michigan Ballot Proposal 'C'"
        }
      },{
        "media": {
          "url": "https://cdm16110.contentdm.oclc.org/utils/getthumbnail/collection/p16110coll7/id/138415",
          "caption": "1994 (November) Michigan Ballot Proposal 'P'",
          "link": "/ballotproposals/items/cdm138415.html",
          "credit": "Michigan Statewide Ballot Proposals"
        },
        "start_date": { 
          "month": "11",
          "day": "",
          "year": "1994"
        },
        "text": {
          "headline": "1994 (November) Michigan Ballot Proposal 'P'"
        }
      },{
        "media": {
          "url": "https://cdm16110.contentdm.oclc.org/utils/getthumbnail/collection/p16110coll7/id/104560",
          "caption": "1996 Michigan Ballot Proposals",
          "link": "/ballotproposals/items/cdm104560.html",
          "credit": "Michigan Statewide Ballot Proposals"
        },
        "start_date": { 
          "year": "1996"
        },
        "text": {
          "headline": "1996 Michigan Ballot Proposals"
        }
      },{
        "media": {
          "url": "https://cdm16110.contentdm.oclc.org/utils/getthumbnail/collection/p16110coll7/id/140876",
          "caption": "1998 Michigan Ballot Proposals",
          "link": "/ballotproposals/items/cdm140876.html",
          "credit": "Michigan Statewide Ballot Proposals"
        },
        "start_date": { 
          "year": "1998"
        },
        "text": {
          "headline": "1998 Michigan Ballot Proposals"
        }
      },{
        "media": {
          "url": "https://cdm16110.contentdm.oclc.org/utils/getthumbnail/collection/p16110coll7/id/104535",
          "caption": "2000 Michigan Ballot Proposals",
          "link": "/ballotproposals/items/cdm104535.html",
          "credit": "Michigan Statewide Ballot Proposals"
        },
        "start_date": { 
          "year": "2000"
        },
        "text": {
          "headline": "2000 Michigan Ballot Proposals"
        }
      },{
        "media": {
          "url": "https://cdm16110.contentdm.oclc.org/utils/getthumbnail/collection/p16110coll7/id/104540",
          "caption": "2002 Michigan Ballot Proposals",
          "link": "/ballotproposals/items/cdm104540.html",
          "credit": "Michigan Statewide Ballot Proposals"
        },
        "start_date": { 
          "year": "2002"
        },
        "text": {
          "headline": "2002 Michigan Ballot Proposals"
        }
      },{
        "media": {
          "url": "https://cdm16110.contentdm.oclc.org/utils/getthumbnail/collection/p16110coll7/id/104554",
          "caption": "2004 Michigan Ballot Proposals",
          "link": "/ballotproposals/items/cdm104554.html",
          "credit": "Michigan Statewide Ballot Proposals"
        },
        "start_date": { 
          "year": "2004"
        },
        "text": {
          "headline": "2004 Michigan Ballot Proposals"
        }
      },{
        "media": {
          "url": "https://cdm16110.contentdm.oclc.org/utils/getthumbnail/collection/p16110coll7/id/104550",
          "caption": "2008 Michigan Ballot Proposals",
          "link": "/ballotproposals/items/cdm104550.html",
          "credit": "Michigan Statewide Ballot Proposals"
        },
        "start_date": { 
          "year": "2008"
        },
        "text": {
          "headline": "2008 Michigan Ballot Proposals"
        }
      },
    ]
}
